toolbox_adk/__init__.py
toolbox_adk/client.py
toolbox_adk/credentials.py
toolbox_adk/tool.py
toolbox_adk/toolset.py
toolbox_adk/version.py
toolbox_adk-0.5.7.dist-info/METADATA
toolbox_adk-0.5.7.dist-info/WHEEL
toolbox_adk-0.5.7.dist-info/top_level.txt
toolbox_adk-0.5.7.dist-info/RECORD
