Metadata-Version: 2.4
Name: toolbox-adk
Version: 0.5.7
Summary: Agent Development Kit Integration for MCP Toolbox
Author-email: Google LLC <googleapis-packages@google.com>
Project-URL: Homepage, https://github.com/googleapis/mcp-toolbox-sdk-python/blob/main/packages/toolbox-adk
Project-URL: Repository, https://github.com/googleapis/mcp-toolbox-sdk-python.git
Project-URL: Bug Tracker, https://github.com/googleapis/mcp-toolbox-sdk-python/issues
Project-URL: Changelog, https://github.com/googleapis/mcp-toolbox-sdk-python/blob/main/packages/toolbox-adk/CHANGELOG.md
Classifier: Intended Audience :: Developers
Classifier: License :: OSI Approved :: Apache Software License
Classifier: Programming Language :: Python
Classifier: Programming Language :: Python :: 3
Classifier: Programming Language :: Python :: 3.10
Classifier: Programming Language :: Python :: 3.11
Classifier: Programming Language :: Python :: 3.12
Classifier: Programming Language :: Python :: 3.13
Classifier: Programming Language :: Python :: 3.14
Classifier: Operating System :: OS Independent
Requires-Python: >=3.10
Requires-Dist: toolbox-core==0.5.7
Requires-Dist: google-auth<3.0.0,>=2.43.0
Requires-Dist: google-auth-oauthlib<2.0.0,>=1.2.0
Requires-Dist: google-adk<2.0.0,>=1.20.0
Requires-Dist: typing-extensions>=4.0.0
Provides-Extra: test
Requires-Dist: black[jupyter]==25.12.0; extra == "test"
Requires-Dist: isort==7.0.0; extra == "test"
Requires-Dist: mypy==1.19.1; extra == "test"
Requires-Dist: pytest==9.0.2; extra == "test"
Requires-Dist: pytest-asyncio==1.3.0; extra == "test"
Requires-Dist: pytest-cov==7.0.0; extra == "test"
Requires-Dist: pytest-mock==3.15.1; extra == "test"
